Workbook

Sheet Assumptions
A1: AI Chatbot ROI Model — Manish Innovations
A2: All blue cells are editable inputs. Update with real figures once the chatbot has live usage data.
A4: Cost Assumptions
A5: Anthropic API cost per query ($) | B5: 0.015 | C5: Approx. cost for a Claude Sonnet call at ~400 tokens; source: Anthropic API pricing page
A6: Hosting cost per month ($) | B6: 7 | C6: Render starter web service tier
A7: Developer maintenance hours/month | B7: 2 | C7: Estimated ongoing maintenance
A8: Developer hourly rate ($) | B8: 15 | C8: Placeholder — update to actual freelance/market rate
A10: Volume Assumptions
A11: Estimated site visitors/month | B11: 2000 | C11: Placeholder — replace with real Google Analytics traffic once available
A12: % of visitors who open the chatbot | B12: 0.08 | C12: Industry benchmark for embedded chat widgets is 5-12%
A13: Avg queries per chat session | B13: 3 | C13: Estimated conversation length
A15: Human Support Comparison
A16: Avg time for human to answer 1 inquiry (min) | B16: 8 | C16: Estimate for email/phone response
A17: Support staff hourly cost ($) | B17: 6 | C17: Approx. loaded cost for support staff in this market
A19: Revenue Impact Assumptions
A20: Chatbot-assisted lead-to-inquiry conversion rate | B20: 0.05 | C20: % of chatbot sessions that convert to a real sales inquiry — placeholder, validate with real data
A21: Avg order value per converted inquiry ($) | B21: 1200 | C21: Placeholder — replace with actual average export order value
A22: Sales close rate on inquiries (%) | B22: 0.2 | C22: Placeholder — replace with actual historical close rate

Sheet Cost-Benefit
A1: Monthly Cost-Benefit Analysis
A3: Metric | B3: Month 1 | C3: Month 2 | D3: Month 3 | E3: Month 4 | F3: Month 5 | G3: Month 6 | H3: Month 7 | I3: Month 8 | J3: Month 9 | K3: Month 10 | L3: Month 11 | M3: Month 12
A4: Chatbot sessions | B4: =Assumptions!$B11*Assumptions!$B12 -> 160 | C4: =Assumptions!$B11*Assumptions!$B12 -> 160 | D4: =Assumptions!$B11*Assumptions!$B12 -> 160 | E4: =Assumptions!$B11*Assumptions!$B12 -> 160 | F4: =Assumptions!$B11*Assumptions!$B12 -> 160 | G4: =Assumptions!$B11*Assumptions!$B12 -> 160 | H4: =Assumptions!$B11*Assumptions!$B12 -> 160 | I4: =Assumptions!$B11*Assumptions!$B12 -> 160 | ... M4: =Assumptions!$B11*Assumptions!$B12 -> 160
A5: Total queries | B5: =B4*Assumptions!$B13 -> 480 | C5: =C4*Assumptions!$B13 -> 480 | D5: =D4*Assumptions!$B13 -> 480 | E5: =E4*Assumptions!$B13 -> 480 | F5: =F4*Assumptions!$B13 -> 480 | G5: =G4*Assumptions!$B13 -> 480 | H5: =H4*Assumptions!$B13 -> 480 | I5: =I4*Assumptions!$B13 -> 480 | ... M5: =M4*Assumptions!$B13 -> 480
A6: API cost ($) | B6: =B5*Assumptions!$B5 -> 7.2 | C6: =C5*Assumptions!$B5 -> 7.2 | D6: =D5*Assumptions!$B5 -> 7.2 | E6: =E5*Assumptions!$B5 -> 7.2 | F6: =F5*Assumptions!$B5 -> 7.2 | G6: =G5*Assumptions!$B5 -> 7.2 | H6: =H5*Assumptions!$B5 -> 7.2 | I6: =I5*Assumptions!$B5 -> 7.2 | ... M6: =M5*Assumptions!$B5 -> 7.2
A7: Hosting cost ($) | B7: =Assumptions!$B6 -> 7 | C7: =Assumptions!$B6 -> 7 | D7: =Assumptions!$B6 -> 7 | E7: =Assumptions!$B6 -> 7 | F7: =Assumptions!$B6 -> 7 | G7: =Assumptions!$B6 -> 7 | H7: =Assumptions!$B6 -> 7 | I7: =Assumptions!$B6 -> 7 | ... M7: =Assumptions!$B6 -> 7
A8: Maintenance cost ($) | B8: =Assumptions!$B7*Assumptions!$B8 -> 30 | C8: =Assumptions!$B7*Assumptions!$B8 -> 30 | D8: =Assumptions!$B7*Assumptions!$B8 -> 30 | E8: =Assumptions!$B7*Assumptions!$B8 -> 30 | F8: =Assumptions!$B7*Assumptions!$B8 -> 30 | G8: =Assumptions!$B7*Assumptions!$B8 -> 30 | H8: =Assumptions!$B7*Assumptions!$B8 -> 30 | I8: =Assumptions!$B7*Assumptions!$B8 -> 30 | ... M8: =Assumptions!$B7*Assumptions!$B8 -> 30
A9: Total chatbot cost ($) | B9: =SUM(B6:B8) -> 44.2 | C9: =SUM(C6:C8) -> 44.2 | D9: =SUM(D6:D8) -> 44.2 | E9: =SUM(E6:E8) -> 44.2 | F9: =SUM(F6:F8) -> 44.2 | G9: =SUM(G6:G8) -> 44.2 | H9: =SUM(H6:H8) -> 44.2 | I9: =SUM(I6:I8) -> 44.2 | ... M9: =SUM(M6:M8) -> 44.2
A10: Converted inquiries | B10: =B4*Assumptions!$B20 -> 8 | C10: =C4*Assumptions!$B20 -> 8 | D10: =D4*Assumptions!$B20 -> 8 | E10: =E4*Assumptions!$B20 -> 8 | F10: =F4*Assumptions!$B20 -> 8 | G10: =G4*Assumptions!$B20 -> 8 | H10: =H4*Assumptions!$B20 -> 8 | I10: =I4*Assumptions!$B20 -> 8 | ... M10: =M4*Assumptions!$B20 -> 8
A11: Closed deals | B11: =B10*Assumptions!$B22 -> 1.6 | C11: =C10*Assumptions!$B22 -> 1.6 | D11: =D10*Assumptions!$B22 -> 1.6 | E11: =E10*Assumptions!$B22 -> 1.6 | F11: =F10*Assumptions!$B22 -> 1.6 | G11: =G10*Assumptions!$B22 -> 1.6 | H11: =H10*Assumptions!$B22 -> 1.6 | I11: =I10*Assumptions!$B22 -> 1.6 | ... M11: =M10*Assumptions!$B22 -> 1.6
A12: Revenue generated ($) | B12: =B11*Assumptions!$B21 -> 1920 | C12: =C11*Assumptions!$B21 -> 1920 | D12: =D11*Assumptions!$B21 -> 1920 | E12: =E11*Assumptions!$B21 -> 1920 | F12: =F11*Assumptions!$B21 -> 1920 | G12: =G11*Assumptions!$B21 -> 1920 | H12: =H11*Assumptions!$B21 -> 1920 | I12: =I11*Assumptions!$B21 -> 1920 | ... M12: =M11*Assumptions!$B21 -> 1920
A13: Human-support-equivalent cost avoided ($) | B13: =(B5*Assumptions!$B16/60)*Assumptions!$B17 -> 384 | C13: =(C5*Assumptions!$B16/60)*Assumptions!$B17 -> 384 | D13: =(D5*Assumptions!$B16/60)*Assumptions!$B17 -> 384 | E13: =(E5*Assumptions!$B16/60)*Assumptions!$B17 -> 384 | F13: =(F5*Assumptions!$B16/60)*Assumptions!$B17 -> 384 | G13: =(G5*Assumptions!$B16/60)*Assumptions!$B17 -> 384 | H13: =(H5*Assumptions!$B16/60)*Assumptions!$B17 -> 384 | I13: =(I5*Assumptions!$B16/60)*Assumptions!$B17 -> 384 | ... M13: =(M5*Assumptions!$B16/60)*Assumptions!$B17 -> 384
A14: Net benefit ($) | B14: =(B12+B13)-B9 -> 2259.8 | C14: =(C12+C13)-C9 -> 2259.8 | D14: =(D12+D13)-D9 -> 2259.8 | E14: =(E12+E13)-E9 -> 2259.8 | F14: =(F12+F13)-F9 -> 2259.8 | G14: =(G12+G13)-G9 -> 2259.8 | H14: =(H12+H13)-H9 -> 2259.8 | I14: =(I12+I13)-I9 -> 2259.8 | ... M14: =(M12+M13)-M9 -> 2259.8

Sheet Summary
A1: ROI Summary
A3: Total annual chatbot cost ($) | B3: ='Cost-Benefit'!B9*12 -> 530.4
A4: Total annual revenue impact ($) | B4: ='Cost-Benefit'!B12*12 -> 23040
A5: Total annual support cost avoided ($) | B5: ='Cost-Benefit'!B13*12 -> 4608
A6: Total annual net benefit ($) | B6: =B4+B5-B3 -> 27117.6
A7: Return on investment (ROI %) | B7: =(B4+B5-B3)/B3 -> 51.126697
A8: Breakeven queries per month (approx.) | B8: ='Cost-Benefit'!B7/(Assumptions!B21*Assumptions!B20*Assumptions!B22/'Cost-Benefit'!B5) -> 280
A10: Interpretation
A11: This model uses placeholder assumptions (blue/yellow cells in the Assumptions tab). Once the chatbot is live, replace visitor count, open rate, and conversion figures with real analytics data from the /analytics/summary endpoint, and this sheet recalculates automatically.
